__symbol_export__.py
__symbol_export__-stubs/__init__.pyi
__symbol_export__-stubs/py.typed
symbol_export-1.0.1.dist-info/licenses/LICENSE
symbol_export-1.0.1.dist-info/METADATA
symbol_export-1.0.1.dist-info/WHEEL
symbol_export-1.0.1.dist-info/top_level.txt
symbol_export-1.0.1.dist-info/RECORD
