Metadata-Version: 2.4
Name: symbol-export
Version: 1.0.1
Summary: Python package module encapsulation toolkit - Enforce public/private symbols at import time
Author-email: AlanBogarin <bogarin01alan@email.com>
License: MIT
Project-URL: Homepage, https://github.com/AlanBogarin/symbol-export
Project-URL: Repository, https://github.com/AlanBogarin/symbol-export
Project-URL: Issues, https://github.com/AlanBogarin/symbol-export/issues
Classifier: Intended Audience :: Developers
Classifier: License :: OSI Approved :: MIT License
Classifier: Programming Language :: Python :: 3.10
Classifier: Programming Language :: Python :: 3.11
Classifier: Programming Language :: Python :: 3.12
Classifier: Programming Language :: Python :: 3.13
Classifier: Programming Language :: Python :: 3.14
Classifier: Operating System :: OS Independent
Classifier: Topic :: Software Development :: Libraries :: Python Modules
Classifier: Topic :: Software Development :: Quality Assurance
Classifier: Typing :: Typed
Requires-Python: >=3.10
License-File: LICENSE
Dynamic: license-file
